{
  "manifest": {
    "publishingInformation": {
      "locales": {
        "en-US": {
          "summary": "ButterCMS Example Skill",
          "examplePhrases": [
            "Alexa open butterCMS-skill"
          ],
          "name": "butterCMS-skill",
          "description": "ButterCMS Example Skill"
        }
      },
      "isAvailableWorldwide": true,
      "testingInstructions": "Sample Testing Instructions.",
      "category": "KNOWLEDGE_AND_TRIVIA",
      "distributionCountries": []
    },
    "apis": {
      "custom": {
        "endpoint": {
          "sourceDir": "lambda/custom",
          "uri": "ask-custom-butterCMS-skill-default"
        }
      }
    },
    "manifestVersion": "1.0"
  }
}
